LICENSE.txt
MANIFEST.in
README.md
setup.cfg
setup.py
demos/__init__.py
demos/decode_demo.py
demos/decode_demo_web.py
demos/sentiment_demo.py
kimalone/__init__.py
kimalone/decode.py
kimalone/version.py
kimalone.egg-info/PKG-INFO
kimalone.egg-info/SOURCES.txt
kimalone.egg-info/dependency_links.txt
kimalone.egg-info/requires.txt
kimalone.egg-info/top_level.txt
kimalone/component/__init__.py
kimalone/component/segment.py
kimalone/component/sentiment.py
kimalone/component/tokenize.py
kimalone/dev/__init__.py
kimalone/dev/demo_tsvreader.py
kimalone/dev/dependency_parser.py
kimalone/dev/document_classifier.py
kimalone/dev/pos_tagger.py
kimalone/dev/reader.py
kimalone/dev/structure.py
kimalone/dev/template/__init__.py
kimalone/dev/template/lexicon.py
kimalone/dev/template/model.py
kimalone/dev/template/state.py
kimalone/dev/template/util.py
kimalone/dev/tests/__init__.py
kimalone/dev/tests/test_lexicon.py
kimalone/dev/tests/test_model.py
kimalone/dev/tests/test_reader.py
kimalone/dev/tests/test_structure.py
kimalone/dev/tests/test_tokenizer.py
kimalone/dev/util/__init__.py
kimalone/dev/util/bisect.py
kimalone/util/__init__.py
kimalone/util/configure.py
kimalone/util/lexicon.py
kimalone/util/string_util.py
kimalone/util/structure.py
tests/__init__.py
tests/tokenizer_test.py