Metadata-Version: 1.1
Name: kimalone
Version: 0.1.14
Summary: The Emory Language Information Toolkit (ELIT).
Home-page: https://github.com/emorynlp/elit
Author: Jinho D. Choi
Author-email: choi@mathcs.emory.edu
License: ALv2
Download-URL: https://github.com/emorynlp/elit/tree/master
Platform: UNKNOWN
Classifier: Development Status :: 3 - Alpha
Classifier: Intended Audience :: Science/Research
Classifier: Intended Audience :: Developers
Classifier: License :: OSI Approved :: Apache Software License
Classifier: Programming Language :: Python :: 3 :: Only
Classifier: Programming Language :: Python :: 3.4
Classifier: Programming Language :: Python :: 3.5
Classifier: Programming Language :: Python :: 3.6
Classifier: Topic :: Scientific/Engineering :: Artificial Intelligence
Classifier: Topic :: Scientific/Engineering :: Information Analysis
Classifier: Operating System :: POSIX
Classifier: Operating System :: Unix
Classifier: Operating System :: MacOS
